{
        "file": "Data_Ingestion_MALZC_ALZCU002",
        "location": "/santander/bi-corp/landing/malzc/fact/alzcu002/partition_date=${partition_date}",
        "destination": "/santander/bi-corp/staging/malzc/fact/alzcu002",
		"createTable": "bi_corp_staging.malzc_alzcu002",
        "extension": "dat",
        "header": false,
        "fixed": true,
        "parquetFiles": 1,
        "compression": "gzip",
        "columns": [
              {
                  "name": "IDE_VALOR",
                  "type": "string",
                  "width": 8
              },
              {
                  "name": "COD_ENTIDAD",
                  "type": "string",
                  "width": 4
              },
              {
                  "name": "COD_SUCURSAL",
                  "type": "string",
                  "width": 4
              },
              {
                  "name": "NRO_CUENTA",
                  "type": "string",
                  "width": 12
              },
              {
                  "name": "COD_DIVISA",
                  "type": "string",
                  "width": 3
              },
              {
                  "name": "NRO_OPERACION",
                  "type": "string",
                  "width": 17
              },
              {
                  "name": "COD_RECH_NACHA",
                  "type": "string",
                  "width": 2
              },
              {
                  "name": "IDE_PAGO_PIRYP",
                  "type": "string",
                  "width": 19
              },
              {
                  "name": "NRO_SECU_PIRYP",
                  "type": "string",
                  "width": 4
              },
              {
                  "name": "IDE_USER_ALTA",
                  "type": "string",
                  "width": 8
              },
              {
                  "name": "IDE_TERM_ALTA",
                  "type": "string",
                  "width": 4
              },
              {
                  "name": "FEC_ALTA",
                  "type": "string",
                  "width": 10
              },
              {
                  "name": "FEC_ACREDITACION",
                  "type": "string",
                  "width": 10
              },
              {
                  "name": "FEC_VENCIMIENTO",
                  "type": "string",
                  "width": 10
              },
              {
                  "name": "NRO_BOLETA_RECAU",
                  "type": "string",
                  "width": 18
              },
              {
                  "name": "NRO_CLIENTE_REF",
                  "type": "string",
                  "width": 22
              },
              {
                  "name": "NRO_CHEQUE_DIG1",
                  "type": "string",
                  "width": 1
              },
              {
                  "name": "NRO_CHEQUE_DIG2",
                  "type": "string",
                  "width": 1
              },
              {
                  "name": "NRO_CHEQUE_DIG3",
                  "type": "string",
                  "width": 1
              },
              {
                  "name": "NRO_CHEQUE_DIG4",
                  "type": "string",
                  "width": 1
              },
              {
                  "name": "NRO_CHEQUE_DIG5",
                  "type": "string",
                  "width": 1
              },
              {
                  "name": "NRO_CHEQUE_DIG6",
                  "type": "string",
                  "width": 1
              },
              {
                  "name": "NRO_CHEQUE_DIG7",
                  "type": "string",
                  "width": 1
              },
              {
                  "name": "NRO_CHEQUE_DIG8",
                  "type": "string",
                  "width": 1
              },
              {
                  "name": "COD_BANCO_GIR",
                  "type": "string",
                  "width": 3
              },
              {
                  "name": "COD_SUC_GIR",
                  "type": "string",
                  "width": 4
              },
              {
                  "name": "NRO_CUENTA_GIR",
                  "type": "string",
                  "width": 11
              },
              {
                  "name": "COD_POST_CHEQUE",
                  "type": "string",
                  "width": 4
              },
              {
                  "name": "IMP_ORIGINAL",
                  "type": "string",
                  "width": 13
              },
              {
                  "name": "IMP_CUADRE",
                  "type": "string",
                  "width": 13
              },
              {
                  "name": "FEC_PRESENTACION",
                  "type": "string",
                  "width": 10
              },
              {
                  "name": "COD_EST_CHEQ_PROC",
                  "type": "string",
                  "width": 2
              },
              {
                  "name": "FEC_EST_CHEQ_PROC",
                  "type": "string",
                  "width": 10
              },
              {
                  "name": "FEC_EST_CHEQ_CANAL",
                  "type": "string",
                  "width": 10
              },
              {
                  "name": "MAR_REG_CONTB",
                  "type": "string",
                  "width": 1
              },
              {
                  "name": "FEC_EGR_STOCK",
                  "type": "string",
                  "width": 10
              },
              {
                  "name": "IDE_USER_ULT_MODF",
                  "type": "string",
                  "width": 8
              },
              {
                  "name": "IDE_TERM_ULT_MODF",
                  "type": "string",
                  "width": 4
              },
              {
                  "name": "TIM_ULT_MODF",
                  "type": "string",
                  "width": 26
              },
              {
                  "name": "TPO_RECAU_PIRYP",
                  "type": "string",
                  "width": 3
              },
              {
                  "name": "COD_CANJE",
                  "type": "string",
                  "width": 2
              },
              {
                  "name": "FISICO_RECIBIDO",
                  "type": "string",
                  "width": 1
              }
          ],
        "extraColumns": [{
                "name": "partition_date",
                "type": "string",
                "value": "${partition_date}",
                "partitionColumn": true,
                "partitionOrder": 1
        }]
}
