{
  "objectMetadata": {
    "active": true,
    "governance": {
      "steward": [
        "A307993"
      ],
      "level": "Basic"
    },
    "table": {
      "name": "aprp_waprp029",
      "title": "Tabla de Caracteristicas de Delivery de Documentos ",
      "schema": "bi_corp_staging",
      "source": "APRP",
      "query": "HQL del ETL",
      "type": "DIM",
      "description": "Tabla de Caracteristicas de Delivery de Documentos ",
      "columns": [
        {
          "name": "WAPRP029_TPO_PIEZA",
          "title": "WAPRP029_TPO_PIEZA",
          "description": "Tipo de pieza",
          "type": "CHAR",
          "personIdentifier": false,
          "decimalSeparator": 0.0,
          "nullable": false,
          "length": 3.0,
          "security": "Publico"
        },
        {
          "name": "WAPRP029_NRO_EMISION",
          "title": "WAPRP029_NRO_EMISION",
          "description": "Número de emisión",
          "type": "DECIMAL",
          "personIdentifier": false,
          "decimalSeparator": ".",
          "nullable": false,
          "length": 8.0,
          "security": "Secreto"
        },
        {
          "name": "WAPRP029_NRO_EMPR",
          "title": "WAPRP029_NRO_EMPR",
          "description": "Número de empresa",
          "type": "DECIMAL",
          "personIdentifier": true,
          "decimalSeparator": ".",
          "nullable": false,
          "length": 11.0,
          "security": "Confidencial"
        },
        {
          "name": "WAPRP029_NRO_DIG_EMPR",
          "title": "WAPRP029_NRO_DIG_EMPR",
          "description": "Número de dígito verificador de empresa",
          "type": "DECIMAL ",
          "personIdentifier": true,
          "decimalSeparator": ".",
          "nullable": false,
          "length": 1.0,
          "security": "Confidencial"
        },
        {
          "name": "WAPRP029_NRO_PROD",
          "title": "WAPRP029_NRO_PROD",
          "description": "Número de producto",
          "type": "DECIMAL ",
          "personIdentifier": true,
          "decimalSeparator": ".",
          "nullable": false,
          "length": 3.0,
          "security": "Confidencial"
        },
        {
          "name": "WAPRP029_NRO_INSTAN",
          "title": "WAPRP029_NRO_INSTAN",
          "description": "Número de instancia",
          "type": "DECIMAL ",
          "personIdentifier": true,
          "decimalSeparator": ".",
          "nullable": false,
          "length": 2.0,
          "security": "Confidencial"
        },
        {
          "name": "WAPRP029_IDE_PGO",
          "title": "WAPRP029_IDE_PGO",
          "description": "Identificación del pago",
          "type": "CHAR    ",
          "personIdentifier": false,
          "decimalSeparator": 0.0,
          "nullable": false,
          "length": 19.0,
          "security": "Publico"
        },
        {
          "name": "WAPRP029_NRO_SUC_DIST",
          "title": "WAPRP029_NRO_SUC_DIST",
          "description": "Sucursal de distribución de la pieza",
          "type": "CHAR",
          "personIdentifier": false,
          "decimalSeparator": 0.0,
          "nullable": false,
          "length": 3.0,
          "security": "Publico"
        },
        {
          "name": "WAPRP029_TPO_DIST",
          "title": "WAPRP029_TPO_DIST",
          "description": "Tipo De Distribución",
          "type": "CHAR",
          "personIdentifier": false,
          "decimalSeparator": 0.0,
          "nullable": false,
          "length": 3.0,
          "security": "Publico"
        },
        {
          "name": "WAPRP029_NRO_EMPR_DIST",
          "title": "WAPRP029_NRO_EMPR_DIST",
          "description": "Empresa de distribución de la pieza",
          "type": "DECIMAL ",
          "personIdentifier": false,
          "decimalSeparator": ".",
          "nullable": false,
          "length": 5.0,
          "security": "Publico"
        },
        {
          "name": "WAPRP029_NOM_ARCHIVO",
          "title": "WAPRP029_NOM_ARCHIVO",
          "description": "Nombre del archivo de medio de distribución",
          "type": "CHAR",
          "personIdentifier": false,
          "decimalSeparator": 0.0,
          "nullable": false,
          "length": 20.0,
          "security": "Publico"
        },
        {
          "name": "WAPRP029_TPO_DESTINO",
          "title": "WAPRP029_TPO_DESTINO",
          "description": "Tipo de destino de distribución",
          "type": "CHAR",
          "personIdentifier": false,
          "decimalSeparator": 0.0,
          "nullable": false,
          "length": 2.0,
          "security": "Publico"
        },
        {
          "name": "WAPRP029_NOM_DESTINO",
          "title": "WAPRP029_NOM_DESTINO",
          "description": "Descripción de tipo de destino",
          "type": "CHAR",
          "personIdentifier": false,
          "decimalSeparator": 0.0,
          "nullable": false,
          "length": 100.0,
          "security": "Publico"
        },
        {
          "name": "WAPRP029_CAN_INSTR",
          "title": "WAPRP029_CAN_INSTR",
          "description": "Cantidad de instrumentos ",
          "type": "DECIMAL ",
          "personIdentifier": false,
          "decimalSeparator": ".",
          "nullable": false,
          "length": 5.0,
          "security": "Publico"
        },
        {
          "name": "WAPRP029_CAN_DAI",
          "title": "WAPRP029_CAN_DAI",
          "description": "Cantidad de días de delivery",
          "type": "DECIMAL ",
          "personIdentifier": false,
          "decimalSeparator":".",
          "nullable": false,
          "length": 5.0,
          "security": "Publico"
        },
        {
          "name": "WAPRP029_NOM_CLTE",
          "title": "WAPRP029_NOM_CLTE",
          "description": "Nombre de cliente receptor instrumento",
          "type": "CHAR",
          "personIdentifier": true,
          "decimalSeparator": 0.0,
          "nullable": false,
          "length": 30.0,
          "security": "Publico"
        },
        {
          "name": "WAPRP029_NRO_CUIT_CLTE",
          "title": "WAPRP029_NRO_CUIT_CLTE",
          "description": "Número de CUIT de cliente receptor",
          "type": "DECIMAL ",
          "personIdentifier": true,
          "decimalSeparator": ".",
          "nullable": false,
          "length": 11.0,
          "security": "Confidencial"
        },
        {
          "name": "WAPRP029_COD_EST_PIEZA",
          "title": "WAPRP029_COD_EST_PIEZA",
          "description": "Estado de pieza de delivery",
          "type": "CHAR    ",
          "personIdentifier": false,
          "decimalSeparator": 0.0,
          "nullable": false,
          "length": 3.0,
          "security": "Publico"
        },
        {
          "name": "WAPRP029_IDE_USER_ALTA",
          "title": "WAPRP029_IDE_USER_ALTA",
          "description": "Identificación de usuario de alta",
          "type": "CHAR",
          "personIdentifier": false,
          "decimalSeparator": 0.0,
          "nullable": false,
          "length": 10.0,
          "security": "Publico"
        },
        {
          "name": "WAPRP029_IDE_TERM_ALTA",
          "title": "WAPRP029_IDE_TERM_ALTA",
          "description": "Identificación terminal de alta",
          "type": "CHAR",
          "personIdentifier": false,
          "decimalSeparator": 0.0,
          "nullable": false,
          "length": 10.0,
          "security": "Publico"
        },
        {
          "name": "WAPRP029_FEC_HRA_ULT_MODF",
          "title": "WAPRP029_FEC_HRA_ULT_MODF",
          "description": "Fecha y hora de la última modificación",
          "type": "CHAR",
          "personIdentifier": false,
          "decimalSeparator": 0.0,
          "nullable": false,
          "length": 26.0,
          "security": "Publico"
        },
        {
          "name": "WAPRP029_IDE_USER_ULT_MODF",
          "title": "WAPRP029_IDE_USER_ULT_MODF",
          "description": "Identificación de usuario de la última modificación",
          "type": "CHAR",
          "personIdentifier": false,
          "decimalSeparator": 0.0,
          "nullable": false,
          "length": 10.0,
          "security": "Publico"
        },
        {
          "name": "WAPRP029_IDE_TERM_ULT_MODF",
          "title": "WAPRP029_IDE_TERM_ULT_MODF",
          "description": "Identificación terminal de la última modificación",
          "type": "CHAR",
          "personIdentifier": false,
          "decimalSeparator": 0.0,
          "nullable": false,
          "length": 5.0,
          "security": "Publico"
        }
      ]
    },
    "schedule": {
      "periodicity": "Daily",
      "loading": {
        "type": "STOCK",
        "delta": "D+1"
      }
    }
  }
}