{
    "objectMetadata": {
        "active": true,
        "governance": {
            "steward": [
                [
                    "A204202"
                ]
            ],
            "level": "Basic"
        },
        "table": {
            "name": "malbgc_bgdttmo_stock",
            "title": "Cuentas Personales",
            "schema": "bi_corp_staging",
            "source": "MALBGC",
            "type": "FACT",
            "description": "Cuentas Personales",
            "columns": [
                {
                    "name": "tmo_concepto",
                    "title": "tmo_concepto",
                    "description": "CODIGO DE CONCEPTO                       ",
                    "type": "string",
                    "personIdentifier": false,
                    "decimalSeparator": "NA",
                    "nullable": false,
                    "length": 4.0
                },
                {
                    "name": "tmo_comision",
                    "title": "tmo_comision",
                    "description": "CODIGO DE LA COMISION",
                    "type": "string",
                    "personIdentifier": false,
                    "decimalSeparator": "NA",
                    "nullable": false,
                    "length": 4.0
                },
                {
                    "name": "tmo_fecha_desde",
                    "title": "tmo_fecha_desde",
                    "description": "FECHA DE INICIO DE VALIDEZ",
                    "type": "string",
                    "personIdentifier": false,
                    "decimalSeparator": "NA",
                    "nullable": false,
                    "length": 10.0
                },
                {
                    "name": "tmo_codigo",
                    "title": "tmo_codigo",
                    "description": "CODIGO POR COMISION",
                    "type": "string",
                    "personIdentifier": false,
                    "decimalSeparator": "NA",
                    "nullable": false,
                    "length": 4.0
                },
                {
                    "name": "tmo_fecha_hasta",
                    "title": "tmo_fecha_hasta",
                    "description": "FECHA FIN DE VALIDEZ",
                    "type": "string",
                    "personIdentifier": false,
                    "decimalSeparator": "NA",
                    "nullable": false,
                    "length": 10.0
                },
                {
                    "name": "tmo_entidad_umo ",
                    "title": "tmo_entidad_umo ",
                    "description": "ENTIDAD ULTIMA MODIFICACION          ",
                    "type": "string",
                    "personIdentifier": false,
                    "decimalSeparator": "NA",
                    "nullable": false,
                    "length": 4.0
                },
                {
                    "name": "tmo_centro_umo  ",
                    "title": "tmo_centro_umo  ",
                    "description": "CENTRO ULTIMA MODIFICACION           ",
                    "type": "string",
                    "personIdentifier": false,
                    "decimalSeparator": "NA",
                    "nullable": false,
                    "length": 4.0
                },
                {
                    "name": "tmo_userid_umo  ",
                    "title": "tmo_userid_umo  ",
                    "description": "USUARIO ULTIMA MODIFICACION          ",
                    "type": "string",
                    "personIdentifier": false,
                    "decimalSeparator": "NA",
                    "nullable": false,
                    "length": 8.0
                },
                {
                    "name": "tmo_netname_umo ",
                    "title": "tmo_netname_umo ",
                    "description": "TERMINAL ULTIMA MODIFICACION         ",
                    "type": "string",
                    "personIdentifier": false,
                    "decimalSeparator": "NA",
                    "nullable": false,
                    "length": 8.0
                },
                {
                    "name": "tmo_timest_umo  ",
                    "title": "tmo_timest_umo  ",
                    "description": "FECHA, HORA DE LA ULTIMA MODIFICACION",
                    "type": "string",
                    "personIdentifier": false,
                    "decimalSeparator": "NA",
                    "nullable": false,
                    "length": 26.0
                }
            ]
        },
        "schedule": {
            "periodicity": "Daily",
            "loading": {
                "type": "INCREMENTAL",
                "delta": "D+1"
            }
        }
    }
}