{
	"file": "getnet_alta_schema",
	"location": "/santander/bi-corp/landing/nps/fact/getnet_alta/partition_date=${partition_date_filter}",
	"destination": "/santander/bi-corp/staging/nps/fact/getnet_alta",
	"createTable": "bi_corp_staging.qualtrics_nps_getnet_alta",
	"extension": "csv",
	"header": true,
	"fixed": false,
	"delimiter": "^",
	"parquetFiles": 1,
	"compression": "gzip",
	"columns": [  {
		"name": "response_id",
		"type": "string"
	},	{
		"name": "variable",
		"type": "string"
	},  {
		"name": "respuesta",
		"type": "string"
	},  {
		"name": "question_id",
		"type": "string"
	},  {
		"name": "question_desc",
		"type": "string"
	},{
		"name": "start_date",
		"type": "string"
	},  {
		"name": "end_date",
		"type": "string"
	},  {
		"name": "status",
		"type": "string"
	},  {
		"name": "ip_address",
		"type": "string"
	},  {
		"name": "progress",
		"type": "string"
	},  {
		"name": "duration",
		"type": "string"
	},  {
		"name": "finished",
		"type": "string"
	},  {
		"name": "recorded_date",
		"type": "string"
	},  {
		"name": "recipient_last_name",
		"type": "string"
	},  {
		"name": "recipient_first_name",
		"type": "string"
	},  {
		"name": "recipient_email",
		"type": "string"
	},  {
		"name": "external_reference",
		"type": "string"
	},  {
		"name": "location_latitude",
		"type": "string"
	},  {
		"name": "location_longitude",
		"type": "string"
	},  {
		"name": "distribution_channel",
		"type": "string"
	},  {
		"name": "user_language",
		"type": "string"
	},  {
		"name": "q1_nps_group",
		"type": "string"
	},	{
		"name": "MOMENTO_CRITICO",
   	    "type": "string"
	},	{
	 	"name": "FECHA_ENCUESTA",
	    "type": "string"
	},	{
	 	"name": "ResponseID",
	    "type": "string"
	},	{
	 	"name": "ID_RESPUESTA",
	    "type": "string"
	},	{
	 	"name": "NUP",
	    "type": "string"
	},	{
	 	"name": "TIPO_DOC",
	    "type": "string"
	},	{
	 	"name": "NRO_DOC",
	    "type": "string"
	},	{
	 	"name": "CUADRANTE",
	    "type": "string"
	},	{
	 	"name": "RENTA",
	    "type": "string"
	},	{
	 	"name": "COLOR",
	    "type": "string"
	},	{
	 	"name": "TELEFONO_FIJO1",
	    "type": "string"
	},	{
	 	"name": "TELEFONO_FIJO2",
	    "type": "string"
	},	{
	 	"name": "TELEFONO_CELULAR1",
	    "type": "string"
	},	{
	 	"name": "TELEFONO_CELULAR2",
	    "type": "string"
	},	{
	 	"name": "COD_SUC_UC",
	    "type": "string"
	},	{
	 	"name": "ZONA",
	    "type": "string"
	},	{
	 	"name": "ANTIGUEDAD",
	    "type": "string"
	},	{
	 	"name": "EDAD",
	    "type": "string"
	},	{
	 	"name": "SEXO",
	    "type": "string"
	},	{
	 	"name": "RENTABILIDAD",
	    "type": "string"
	},	{
	 	"name": "MER_ACCOUNT_ENABLED",
	    "type": "string"
	},	{
	 	"name": "MER_CATEGORY",
	    "type": "string"
	},	{
	 	"name": "MER_CREATED_AT",
	    "type": "string"
	},	{
	 	"name": "MER_CUIT",
	    "type": "string"
	},	{
	 	"name": "MER_DOCUMENT_NUMBER",
	    "type": "string"
	},	{
		"name": "MER_EMAIL",
	    "type": "string"
	},	{
	 	"name": "MER_FIRST_NAME",
	    "type": "string"
	},	{
	 	"name": "MER_LAST_NAME",
	    "type": "string"
	},	{
	 	"name": "MER_LEGAL_NAME",
	    "type": "string"
	},	{
	 	"name": "MER_NAME",
	    "type": "string"
	},	{
	 	"name": "MER_PHONE",
	    "type": "string"
	},	{
	 	"name": "MER_SUBSIDIARY_ENABLED",
	    "type": "string"
	},	{
	 	"name": "MER_TYPE",
	    "type": "string"
	},	{
	 	"name": "FECHA_ENVIO",
	    "type": "string"
	},	{
	 	"name": "GATEWAY ALIAS",
	    "type": "string"
	},	{
	 	"name": "RecipientID",
	    "type": "string"
	},	{
	 	"name": "MARCA_GES_REMOTO",
	    "type": "string"
	},	{
	 	"name": "MARCA_WOMEN",
	    "type": "string"
	},	{
	 	"name": "MARCA_UNIV",
	    "type": "string"
	},	{
	 	"name": "MARCA_CTA_BLANCA",
	    "type": "string"
	},	{
	 	"name": "MER_CODIGO_CANAL",
	    "type": "string"
	},	{
	 	"name": "transactionDate",
	    "type": "string"
	},	{
	 	"name": "EMAIL",
	    "type": "string"
	},	{
	 	"name": "NPS_GETNET_ALTA",
	    "type": "string"
	},	{
	 	"name": "NPS_COMENTARIO_GETNET_ALTA",
	    "type": "string"
	}],
	"extraColumns": [{
		"name": "partition_date",
		"type": "string",
		"value": "${partition_date_filter}",
		"partitionColumn": true,
		"partitionOrder": 1
	}]
}