{
  "tables": [
    {
      "source": "zendesk_tk",
      "type": "fact",
      "name": "santander-ar",
      "filePrefix": "zendesk_tk_santander-ar_"
    },
    {
      "source": "zendesk_tk",
      "type": "fact",
      "name": "comex-santander",
      "filePrefix": "zendesk_tk_comex-santander_"
    },
    {
      "source": "zendesk_tk",
      "type": "fact",
      "name": "puc-santander",
      "filePrefix": "zendesk_tk_puc-santander_"
    },
    {
      "source": "zendesk_tk",
      "type": "fact",
      "name": "globalgetnet",
      "filePrefix": "zendesk_tk_globalgetnet_"
    },
    {
      "source": "zendesk_usr",
      "type": "fact",
      "name": "santander-ar",
      "filePrefix": "zendesk_usr_santander-ar_"
    },
    {
      "source": "zendesk_usr",
      "type": "fact",
      "name": "comex-santander",
      "filePrefix": "zendesk_usr_comex-santander_"
    },
    {
      "source": "zendesk_usr",
      "type": "fact",
      "name": "puc-santander",
      "filePrefix": "zendesk_usr_puc-santander_"
    },
    {
      "source": "zendesk_usr",
      "type": "fact",
      "name": "globalgetnet",
      "filePrefix": "zendesk_usr_globalgetnet_"
    },
    {
      "source": "zendesk_brands",
      "type": "dim",
      "name": "santander-ar",
      "filePrefix": "zendesk_brands_santander-ar_"
    },
    {
      "source": "zendesk_brands",
      "type": "dim",
      "name": "comex-santander",
      "filePrefix": "zendesk_brands_comex-santander_"
    },
    {
      "source": "zendesk_brands",
      "type": "dim",
      "name": "puc-santander",
      "filePrefix": "zendesk_brands_puc-santander_"
    },
    {
      "source": "zendesk_gr",
      "type": "dim",
      "name": "santander-ar",
      "filePrefix": "zendesk_gr_santander-ar_"
    },
    {
      "source": "zendesk_gr",
      "type": "dim",
      "name": "comex-santander",
      "filePrefix": "zendesk_gr_comex-santander_"
    },
    {
      "source": "zendesk_gr",
      "type": "dim",
      "name": "puc-santander",
      "filePrefix": "zendesk_gr_puc-santander_"
    },
    {
      "source": "zendesk_tk_fields",
      "type": "dim",
      "name": "santander-ar",
      "filePrefix": "zendesk_tk_fields_santander-ar_"
    },
    {
      "source": "zendesk_tk_fields",
      "type": "dim",
      "name": "comex-santander",
      "filePrefix": "zendesk_tk_fields_comex-santander_"
    },
    {
      "source": "zendesk_tk_fields",
      "type": "dim",
      "name": "puc-santander",
      "filePrefix": "zendesk_tk_fields_puc-santander_"
    },
    {
      "source": "zendesk_tk_forms",
      "type": "dim",
      "name": "santander-ar",
      "filePrefix": "zendesk_tk_forms_santander-ar_"
    },
    {
      "source": "zendesk_tk_forms",
      "type": "dim",
      "name": "comex-santander",
      "filePrefix": "zendesk_tk_forms_comex-santander_"
    },
    {
      "source": "zendesk_tk_forms",
      "type": "dim",
      "name": "puc-santander",
      "filePrefix": "zendesk_tk_forms_puc-santander_"
    }

  ],
  "trigger": {
    "condition": "all",
    "dag": "LOAD_STG_ZENDESK-Daily"
  }
}