{
  "table": "bi_corp_common.stk_adm_pyme_operaciones",
  "partition_date": "${partition_date}",
  "controls": [
    {
      "control_id": "duplicates",
      "field_to_check": ["cod_adm_secu_f487"]
    },
    {
      "control_id": "null_values",
      "field_to_check": ["cod_adm_tramite","cod_adm_penumper","cod_adm_secu_f487","cod_prod_producto","int_adm_secuencia","fc_adm_monto","ds_adm_pecodmon","int_adm_plazo","ds_adm_unidad_plazo","dt_adm_vencimiento","dec_adm_tasa","ds_adm_tipo_tasa","dec_adm_costo","ds_adm_destino_fondos","ds_adm_clase_operacion","dt_adm_fecha_acreditacion","int_adm_numero_cta_cte","flag_adm_dentro_limite","ds_adm_estado_f487","dt_adm_fecha_operacion","ds_adm_peusualt","ds_adm_operacion_especial","fc_adm_mon_f487_original","int_adm_plazo_f487_original","int_adm_nro_comprobante","flag_adm_mar_reutiliza_veraz","cod_adm_nup","cod_adm_segmentoduro","ds_adm_segmento","ds_adm_subsegmento","cod_adm_cuadrante"],
      "threshold": 0.00
    },
    {
      "control_id": "date_format",
      "field_to_check": ["dt_adm_vencimiento","dt_adm_fecha_acreditacion","dt_adm_fecha_operacion","dt_adm_fec_reducc_iibb","dt_adm_fec_reducc_sell","dt_adm_pefecalt","dt_adm_pefecmod","dt_adm_fecha_liquidacion","dt_adm_inicio_cobro","dt_adm_primer_pago_intereses","dt_adm_fec_adelanto_cesion","dt_adm_fec_carga","dt_adm_fec_cierre","dt_adm_fec_envio_sw","dt_adm_fec_respuesta_sw","dt_adm_fec_ini_resol_zg","dt_adm_fec_fin_resol_zg","dt_adm_fec_ini_resol_sup","dt_adm_fec_fin_resol_sup","dt_adm_fec_envio_veraz","dt_adm_fec_respuesta_veraz","dt_adm_fec_ini_resol_op","dt_adm_fec_fin_resol_op","dt_adm_fec_resol_scoring","dt_adm_fec_resol_zona_gris","dt_adm_fec_resol_scoring_zona_gris","dt_adm_fec_resol_supervision"],
      "pattern": "yyyy-MM-dd HH:mm:ss.SSS",
      "threshold": 0.00
    }
	  ]
}